pageutils/__init__.py
wagtail_pageutils-0.0.1.dist-info/LICENSE
wagtail_pageutils-0.0.1.dist-info/METADATA
wagtail_pageutils-0.0.1.dist-info/WHEEL
wagtail_pageutils-0.0.1.dist-info/RECORD
